{"C9evM/nzuRXUpTAYkWDxSw==":"favicon-96x96.png","Qipuf6ohbZjiMJ73W4T1NA==":"intro-bg-2000x1125.jpg","xQe/S2KuPLKFcBwAUvCElQ==":"corkino-550x301.jpg","guARySyCMXIH0ZGRT3Ck+Q==":"crm-551x301.jpg","MIB4gy01PwKivgIydUPpSQ==":"maxmsp-551x301.jpg","60I6nlY7nMySGXupVgP6ig==":"dibox-551x301.jpg","oUtFvL8+JBNc8d9cUiqkug==":"bertoncini-550x301.jpg","TUDcQiusb2c9LiGvPw2TVw==":"scecilia-551x301.jpg","+X0uX4cAiSVqy932vICFHA==":"bg-1591x1061.jpg","cL9TaHM6369xw4+6XEKV4w==":"corkino-2136x1202.jpeg","6FXVnpE9Ujq3tNulSVm9XQ==":"corkino-2000x1125.jpeg","90sbiexh3rL30ugioGZlNw==":"cleopatra_negra-acqua-686x343.png","6wgbFzWkZ4Yt5eCdbR0iSA==":"cleopatra_negra-acqua-1-686x343.png","j8udMjoiW3cHR3DU7P1Rwg==":"manual_cover-600x201.png","GOBjmO83vC+3hPJE78io9g==":"manual_cover-1-600x201.png","4pjDlIvuFRfP7zid266jww==":"corkino-1288x725.jpg","uaRrwA9H0RYOzCM6UV/TvQ==":"corkino-1288x725.jpeg","NcKD6S8txUDPa3axCfVo6g==":"gen~%20svf.gif","Md4ZMKVmawLQGsJWmAKaEA==":"logo_faust_simple_bleu-390x390.png","lPsY2/4hBr2rowxwdCLRjw==":"cycling_74_logo.svg-432x237.png","a6y74h5D+ca3n63gtLYKiA==":"corkino-432x243.png","TUv8lkJP3MTIML0SL96QLQ==":"dibox-432x236.jpg","6OKoAckECTrSzerlJj8jUA==":"favicon-96x121.png","v7qcXIvXNFBaW6q+uEIjgw==":"post_corkino-1201x401.png"}